pybw_comic/__init__.py
pybw_comic/convert/__init__.py
pybw_comic/convert/image_to_pdf.py
pybw_comic/engines/__init__.py
pybw_comic/engines/_todo_dmzj_cn.py
pybw_comic/engines/_todo_dmzj_requests.py
pybw_comic/engines/cnanjie.py
pybw_comic/engines/copymanga.py
pybw_comic/engines/dmzj_selenium.py
pybw_comic/engines/manhuaDB.py
pybw_comic/engines/maofly.py
pybw_comic/engines/mhkan.py
pybw_comic/engines/www_1kkk.py
pybw_comic/engines/xmanhua.py
pybw_comic/scripts/__init__.py
pybw_comic/scripts/comic.py
pybw_comic/scripts/wnacg.py
pybw_comic-25.3.3.1.data/scripts/comic.py
pybw_comic-25.3.3.1.data/scripts/wnacg.py
pybw_comic-25.3.3.1.dist-info/LICENSE
pybw_comic-25.3.3.1.dist-info/METADATA
pybw_comic-25.3.3.1.dist-info/WHEEL
pybw_comic-25.3.3.1.dist-info/entry_points.txt
pybw_comic-25.3.3.1.dist-info/top_level.txt
pybw_comic-25.3.3.1.dist-info/RECORD
