Metadata-Version: 2.1
Name: pybw-comic
Version: 25.3.3.1
Summary: comic spider
Home-page: https://gitee.com/pubowei/comic
Author: Bowei Pu
Author-email: pubowei@foxmail.com
License: MIT
Project-URL: Docs, https://gitee.com/pubowei/comic
Project-URL: Package, https://pypi.org/project/pybw
Project-URL: Repo, https://gitee.com/pubowei/comic
Keywords: comic,spider
Platform: UNKNOWN
Classifier: Development Status :: 4 - Beta
Classifier: Intended Audience :: Science/Research
Classifier: License :: OSI Approved :: MIT License
Classifier: Operating System :: OS Independent
Classifier: Programming Language :: Python :: 3.6
Requires-Python: >=3.6
License-File: LICENSE
